vector_rag_tool/__init__.py
vector_rag_tool/cli.py
vector_rag_tool/completion.py
vector_rag_tool/logging_config.py
vector_rag_tool/utils.py
vector_rag_tool/commands/__init__.py
vector_rag_tool/commands/index.py
vector_rag_tool/commands/query.py
vector_rag_tool/commands/store.py
vector_rag_tool/core/__init__.py
vector_rag_tool/core/backend.py
vector_rag_tool/core/backend_factory.py
vector_rag_tool/core/chunking.py
vector_rag_tool/core/converter.py
vector_rag_tool/core/embeddings.py
vector_rag_tool/core/faiss_backend.py
vector_rag_tool/core/file_detector.py
vector_rag_tool/core/models.py
vector_rag_tool/core/s3vectors_backend.py
vector_rag_tool/services/__init__.py
vector_rag_tool/services/indexer.py
vector_rag_tool/services/querier.py
vector_rag_tool-0.1.0.dist-info/METADATA
vector_rag_tool-0.1.0.dist-info/WHEEL
vector_rag_tool-0.1.0.dist-info/entry_points.txt
vector_rag_tool-0.1.0.dist-info/licenses/LICENSE
vector_rag_tool-0.1.0.dist-info/RECORD
