Metadata-Version: 2.4
Name: vector-rag-tool
Version: 0.1.0
Summary: RAG tool with local FAISS and remote S3 Vectors backends, using Ollama embeddings
Project-URL: Homepage, https://github.com/dnvriend/vector-rag-tool
Project-URL: Repository, https://github.com/dnvriend/vector-rag-tool
Project-URL: Issues, https://github.com/dnvriend/vector-rag-tool/issues
Author-email: Dennis Vriend <dvriend@ilionx.com>
License: MIT
License-File: LICENSE
Keywords: cli,embeddings,faiss,ollama,rag,semantic-search,vector-search
Classifier: Development Status :: 4 - Beta
Classifier: Intended Audience :: Developers
Classifier: License :: OSI Approved :: MIT License
Classifier: Programming Language :: Python :: 3
Classifier: Programming Language :: Python :: 3.13
Classifier: Topic :: Software Development :: Libraries
Classifier: Topic :: Text Processing :: Indexing
Requires-Python: >=3.13
Requires-Dist: boto3>=1.35.0
Requires-Dist: click>=8.1.7
Requires-Dist: faiss-cpu>=1.7.0
Requires-Dist: langchain-text-splitters>=0.3.0
Requires-Dist: numpy>=1.24.0
Requires-Dist: ollama>=0.1.0
Requires-Dist: pyyaml>=6.0.0
Requires-Dist: tqdm>=4.66.0
Provides-Extra: documents
Requires-Dist: markitdown[all]>=0.1.0; extra == 'documents'
Requires-Dist: openai>=1.0.0; extra == 'documents'
